logs_weasel/__init__.py
logs_weasel/main.py
logs_weasel-2.2.dist-info/LICENSE
logs_weasel-2.2.dist-info/METADATA
logs_weasel-2.2.dist-info/WHEEL
logs_weasel-2.2.dist-info/top_level.txt
logs_weasel-2.2.dist-info/RECORD
