Metadata-Version: 2.1
Name: logs-weasel
Version: 2.2
Summary: Easy-to-read display of logs with save to db redis and sending notifications in telegram
Home-page: https://github.com/gnlxpy/logs_weasel
Author: Aleksei Goncharov
Author-email: gnlx@proton.me
License: MIT
Classifier: Programming Language :: Python :: 3
Classifier: License :: OSI Approved :: MIT License
Classifier: Operating System :: OS Independent
Requires-Python: >=3.10
License-File: LICENSE
Requires-Dist: async-timeout==4.0.2
Requires-Dist: certifi==2024.6.2
Requires-Dist: charset-normalizer==3.3.2
Requires-Dist: idna==3.7
Requires-Dist: redis==4.5.4
Requires-Dist: requests==2.32.3
Requires-Dist: urllib3==2.2.2
